{
  "_class": "group",
  "booleanOperation": -1,
  "do_objectID": "C8299A94-D8C1-4342-A809-D4B744112735",
  "exportOptions": {
    "_class": "exportOptions",
    "exportFormats": [
    ],
    "includedLayerIds": [
    ],
    "layerOptions": 0,
    "shouldTrim": false
  },
  "frame": {
    "_class": "rect",
    "constrainProportions": false,
    "height": 21.00000000000002,
    "width": 79.00000000000006,
    "x": 0,
    "y": 0
  },
  "hasClickThrough": false,
  "isFixedToViewport": false,
  "isFlippedHorizontal": false,
  "isFlippedVertical": false,
  "isLocked": false,
  "isVisible": true,
  "layerListExpandedType": 0,
  "layers": [
    {
      "class": "shapeGroup",
      "id": "1371410C-895E-4121-9507-0BD048CA7263"
    },
    {
      "class": "shapeGroup",
      "id": "BFE6D6E5-A016-46AB-8199-B2B507E1973B"
    },
    {
      "class": "shapeGroup",
      "id": "20D3BED3-D211-4BE1-9DDE-D53C6C8FE4AB"
    },
    {
      "class": "shapeGroup",
      "id": "A40C89F0-845F-4448-B570-7CEDB15F55CD"
    }
  ],
  "name": "Group_3",
  "nameIsFixed": false,
  "resizingConstraint": 63,
  "resizingType": 0,
  "rotation": 0,
  "shouldBreakMaskChain": false,
  "style": {
    "_class": "style",
    "endMarkerType": 0,
    "fills": [
      {
        "_class": "fill",
        "color": {
          "_class": "color",
          "alpha": 1,
          "blue": 0,
          "green": 0,
          "red": 0
        },
        "fillType": 0,
        "isEnabled": true,
        "noiseIndex": 0,
        "noiseIntensity": 0,
        "patternFillType": 1,
        "patternTileScale": 1
      }
    ],
    "miterLimit": 10,
    "startMarkerType": 0,
    "windingRule": 1
  }
}