{
  "_class": "shapePath",
  "booleanOperation": -1,
  "do_objectID": "A2A07A7C-00F1-424B-A4DF-273FA60335EF",
  "edited": true,
  "exportOptions": {
    "_class": "exportOptions",
    "exportFormats": [
    ],
    "includedLayerIds": [
    ],
    "layerOptions": 0,
    "shouldTrim": false
  },
  "frame": {
    "_class": "rect",
    "constrainProportions": false,
    "height": 5.67044486078608,
    "width": 5.670521346171991,
    "x": 5.678188317757443,
    "y": 5.682766649768364
  },
  "isClosed": true,
  "isFixedToViewport": false,
  "isFlippedHorizontal": false,
  "isFlippedVertical": false,
  "isLocked": false,
  "isVisible": true,
  "layerListExpandedType": 0,
  "name": "Path",
  "nameIsFixed": false,
  "pointRadiusBehaviour": 1,
  "points": [
    {
      "_class": "curvePoint",
      "cornerRadius": 0,
      "curveFrom": "{0.22427967472419591, 1}",
      "curveMode": 2,
      "curveTo": "{0.77572032527580415, 1}",
      "hasCurveFrom": true,
      "hasCurveTo": true,
      "point": "{0.50000557743148133, 1}"
    },
    {
      "_class": "curvePoint",
      "cornerRadius": 0,
      "curveFrom": "{0, 0.22428832768159915}",
      "curveMode": 2,
      "curveTo": "{0, 0.77572282705693385}",
      "hasCurveFrom": true,
      "hasCurveTo": true,
      "point": "{0, 0.50000000000000011}"
    },
    {
      "_class": "curvePoint",
      "cornerRadius": 0,
      "curveFrom": "{0.77572032527580415, 0}",
      "curveMode": 2,
      "curveTo": "{0.22427967472419622, 0}",
      "hasCurveFrom": true,
      "hasCurveTo": true,
      "point": "{0.50000557743148133, 0}"
    },
    {
      "_class": "curvePoint",
      "cornerRadius": 0,
      "curveFrom": "{1, 0.77572282705693352}",
      "curveMode": 2,
      "curveTo": "{1, 0.22428832768159915}",
      "hasCurveFrom": true,
      "hasCurveTo": true,
      "point": "{1, 0.50000000000000011}"
    }
  ],
  "resizingConstraint": 63,
  "resizingType": 0,
  "rotation": 0,
  "shouldBreakMaskChain": false
}