{
  "_class": "shapePath",
  "booleanOperation": -1,
  "do_objectID": "0E9EB93A-8AB3-4116-9C5F-96FE7ABDA22D",
  "edited": true,
  "exportOptions": {
    "_class": "exportOptions",
    "exportFormats": [
    ],
    "includedLayerIds": [
    ],
    "layerOptions": 0,
    "shouldTrim": false
  },
  "frame": {
    "_class": "rect",
    "constrainProportions": false,
    "height": 7.99999999999999,
    "width": 2.000000000000004,
    "x": 0,
    "y": 0
  },
  "isClosed": true,
  "isFixedToViewport": false,
  "isFlippedHorizontal": false,
  "isFlippedVertical": false,
  "isLocked": false,
  "isVisible": true,
  "layerListExpandedType": 0,
  "name": "Path",
  "nameIsFixed": false,
  "pointRadiusBehaviour": 1,
  "points": [
    {
      "_class": "curvePoint",
      "cornerRadius": 0,
      "curveFrom": "{0, 0}",
      "curveMode": 1,
      "curveTo": "{0, 0}",
      "hasCurveFrom": false,
      "hasCurveTo": false,
      "point": "{0, 0}"
    },
    {
      "_class": "curvePoint",
      "cornerRadius": 0,
      "curveFrom": "{0, 0.97267253358036143}",
      "curveMode": 4,
      "curveTo": "{0, 0.9388605836035202}",
      "hasCurveFrom": true,
      "hasCurveTo": false,
      "point": "{0, 0.9388605836035202}"
    },
    {
      "_class": "curvePoint",
      "cornerRadius": 0,
      "curveFrom": "{0.15999999999999992, 1}",
      "curveMode": 4,
      "curveTo": "{0.071515151515151615, 1}",
      "hasCurveFrom": false,
      "hasCurveTo": true,
      "point": "{0.15999999999999992, 1}"
    },
    {
      "_class": "curvePoint",
      "cornerRadius": 0,
      "curveFrom": "{0.92848484848484869, 1}",
      "curveMode": 4,
      "curveTo": "{0.84000000000000008, 1}",
      "hasCurveFrom": true,
      "hasCurveTo": false,
      "point": "{0.84000000000000008, 1}"
    },
    {
      "_class": "curvePoint",
      "cornerRadius": 0,
      "curveFrom": "{1, 0.9388605836035202}",
      "curveMode": 4,
      "curveTo": "{1, 0.97267253358036143}",
      "hasCurveFrom": false,
      "hasCurveTo": true,
      "point": "{1, 0.9388605836035202}"
    },
    {
      "_class": "curvePoint",
      "cornerRadius": 0,
      "curveFrom": "{0.83030303030303021, 0.28670680870773507}",
      "curveMode": 4,
      "curveTo": "{1, 0.29504400185270968}",
      "hasCurveFrom": true,
      "hasCurveTo": false,
      "point": "{1, 0.29504400185270968}"
    },
    {
      "_class": "curvePoint",
      "cornerRadius": 0,
      "curveFrom": "{0.5515151515151514, 0.21120889300602128}",
      "curveMode": 4,
      "curveTo": "{0.67393939393939373, 0.25798981009726735}",
      "hasCurveFrom": false,
      "hasCurveTo": true,
      "point": "{0.5515151515151514, 0.21120889300602128}"
    }
  ],
  "resizingConstraint": 63,
  "resizingType": 0,
  "rotation": 0,
  "shouldBreakMaskChain": false
}