{
  "_class": "shapeGroup",
  "booleanOperation": -1,
  "clippingMaskMode": 0,
  "do_objectID": "78EB00C5-D1F6-4464-B5D3-19DEFB0F097D",
  "exportOptions": {
    "_class": "exportOptions",
    "do_objectID": "673F2591-C47E-4577-9342-0502458D19B1",
    "exportFormats": [
    ],
    "includedLayerIds": [
    ],
    "layerOptions": 0,
    "shouldTrim": false
  },
  "frame": {
    "_class": "rect",
    "constrainProportions": false,
    "do_objectID": "3A518DCF-53CF-4595-A623-1A98C5D9D508",
    "height": 46.23206847958527,
    "width": 37.02067318807805,
    "x": 9.884650272687102,
    "y": 0.00005502443282357946
  },
  "hasClickThrough": false,
  "hasClippingMask": false,
  "isFixedToViewport": false,
  "isFlippedHorizontal": false,
  "isFlippedVertical": false,
  "isLocked": false,
  "isVisible": true,
  "layerListExpandedType": 1,
  "layers": [
    {
      "class": "shapePath",
      "id": "34B438EF-AF41-4102-88D2-098B3B516F7B"
    },
    {
      "class": "shapePath",
      "id": "8ACF5EF9-867B-4716-94CC-B5195027AF5E"
    }
  ],
  "name": "Path_9",
  "nameIsFixed": false,
  "resizingConstraint": 63,
  "resizingType": 0,
  "rotation": 0,
  "shouldBreakMaskChain": false,
  "style": {
    "_class": "style",
    "do_objectID": "64644E35-FFE4-4A92-9F80-E06C0E6169DE",
    "endMarkerType": 0,
    "fills": [
      {
        "_class": "fill",
        "color": {
          "_class": "color",
          "alpha": 1,
          "blue": 0,
          "green": 0,
          "red": 0
        },
        "fillType": 1,
        "gradient": {
          "_class": "gradient",
          "elipseLength": 0,
          "from": "{-0.76600000000000001, 1.5229999999999999}",
          "gradientType": 0,
          "stops": [
            {
              "_class": "gradientStop",
              "color": {
                "_class": "color",
                "alpha": 1,
                "blue": 0.3529411764705882,
                "green": 0.1019607843137255,
                "red": 0.9254901960784314
              },
              "position": 0
            },
            {
              "_class": "gradientStop",
              "color": {
                "_class": "color",
                "alpha": 1,
                "blue": 0.01568627450980392,
                "green": 0.8,
                "red": 1
              },
              "position": 1
            }
          ],
          "to": "{0.86299999999999999, 0.17299999999999999}"
        },
        "isEnabled": true,
        "noiseIndex": 0,
        "noiseIntensity": 0,
        "patternFillType": 1,
        "patternTileScale": 1
      }
    ],
    "miterLimit": 10,
    "startMarkerType": 0,
    "windingRule": 0
  },
  "windingRule": 0
}