{
  "_class": "shapeGroup",
  "booleanOperation": -1,
  "clippingMaskMode": 0,
  "do_objectID": "7BE15234-A2C2-465F-8618-E238EFFB927C",
  "exportOptions": {
    "_class": "exportOptions",
    "do_objectID": "6D430798-E40C-4C0B-A72B-AE86E3CFB488",
    "exportFormats": [
    ],
    "includedLayerIds": [
    ],
    "layerOptions": 0,
    "shouldTrim": false
  },
  "frame": {
    "_class": "rect",
    "constrainProportions": true,
    "do_objectID": "01F41B42-0723-415E-A89C-520947E84648",
    "height": 79.67777777777778,
    "width": 79.67777777777775,
    "x": 602,
    "y": 887
  },
  "hasClickThrough": false,
  "hasClippingMask": false,
  "isFixedToViewport": false,
  "isFlippedHorizontal": false,
  "isFlippedVertical": false,
  "isLocked": false,
  "isVisible": true,
  "layerListExpandedType": 0,
  "layers": [
    {
      "class": "oval",
      "id": "55ADB606-A5F9-4714-BE62-584BC0FECF7E"
    }
  ],
  "name": "Oval Copy 4",
  "nameIsFixed": false,
  "resizingConstraint": 63,
  "resizingType": 0,
  "rotation": 0,
  "shouldBreakMaskChain": false,
  "style": {
    "_class": "style",
    "borders": [
      {
        "_class": "border",
        "color": {
          "_class": "color",
          "alpha": 1,
          "blue": 0.592,
          "green": 0.592,
          "red": 0.592
        },
        "fillType": 0,
        "isEnabled": false,
        "position": 0,
        "thickness": 1
      }
    ],
    "do_objectID": "7079FFD7-0234-4604-A913-FB634A64BD3D",
    "endMarkerType": 0,
    "fills": [
      {
        "_class": "fill",
        "color": {
          "_class": "color",
          "alpha": 1,
          "blue": 0.9294117647058824,
          "green": 0.9294117647058824,
          "red": 0.9294117647058824
        },
        "fillType": 0,
        "isEnabled": true,
        "noiseIndex": 0,
        "noiseIntensity": 0,
        "patternFillType": 1,
        "patternTileScale": 1
      }
    ],
    "miterLimit": 10,
    "startMarkerType": 0,
    "windingRule": 0
  },
  "windingRule": 0
}