{
  "_class": "shapePath",
  "booleanOperation": -1,
  "do_objectID": "5A42D05C-043D-45D6-A5CB-B44C73FAB41D",
  "edited": true,
  "exportOptions": {
    "_class": "exportOptions",
    "exportFormats": [
    ],
    "includedLayerIds": [
    ],
    "layerOptions": 0,
    "shouldTrim": false
  },
  "frame": {
    "_class": "rect",
    "constrainProportions": false,
    "height": 7.181663837011889,
    "width": 4.879665148245799,
    "x": 24.04127707184511,
    "y": 0.1196943972835322
  },
  "isClosed": true,
  "isFixedToViewport": false,
  "isFlippedHorizontal": false,
  "isFlippedVertical": false,
  "isLocked": false,
  "isVisible": true,
  "layerListExpandedType": 0,
  "name": "Path",
  "nameIsFixed": false,
  "pointRadiusBehaviour": 1,
  "points": [
    {
      "_class": "curvePoint",
      "cornerRadius": 0,
      "curveFrom": "{0.60975609756097648, 1}",
      "curveMode": 1,
      "curveTo": "{0.60975609756097648, 1}",
      "hasCurveFrom": false,
      "hasCurveTo": false,
      "point": "{0.60975609756097648, 1}"
    },
    {
      "_class": "curvePoint",
      "cornerRadius": 0,
      "curveFrom": "{0.41463414634146467, 1}",
      "curveMode": 1,
      "curveTo": "{0.41463414634146467, 1}",
      "hasCurveFrom": false,
      "hasCurveTo": false,
      "point": "{0.41463414634146467, 1}"
    },
    {
      "_class": "curvePoint",
      "cornerRadius": 0,
      "curveFrom": "{0.41463414634146467, 0.1166666666666667}",
      "curveMode": 1,
      "curveTo": "{0.41463414634146467, 0.1166666666666667}",
      "hasCurveFrom": false,
      "hasCurveTo": false,
      "point": "{0.41463414634146467, 0.1166666666666667}"
    },
    {
      "_class": "curvePoint",
      "cornerRadius": 0,
      "curveFrom": "{0, 0.1166666666666667}",
      "curveMode": 1,
      "curveTo": "{0, 0.1166666666666667}",
      "hasCurveFrom": false,
      "hasCurveTo": false,
      "point": "{0, 0.1166666666666667}"
    },
    {
      "_class": "curvePoint",
      "cornerRadius": 0,
      "curveFrom": "{0, 0}",
      "curveMode": 1,
      "curveTo": "{0, 0}",
      "hasCurveFrom": false,
      "hasCurveTo": false,
      "point": "{0, 0}"
    },
    {
      "_class": "curvePoint",
      "cornerRadius": 0,
      "curveFrom": "{1, 0}",
      "curveMode": 1,
      "curveTo": "{1, 0}",
      "hasCurveFrom": false,
      "hasCurveTo": false,
      "point": "{1, 0}"
    },
    {
      "_class": "curvePoint",
      "cornerRadius": 0,
      "curveFrom": "{1, 0.1166666666666667}",
      "curveMode": 1,
      "curveTo": "{1, 0.1166666666666667}",
      "hasCurveFrom": false,
      "hasCurveTo": false,
      "point": "{1, 0.1166666666666667}"
    },
    {
      "_class": "curvePoint",
      "cornerRadius": 0,
      "curveFrom": "{0.58536585365853877, 0.1166666666666667}",
      "curveMode": 1,
      "curveTo": "{0.58536585365853877, 0.1166666666666667}",
      "hasCurveFrom": false,
      "hasCurveTo": false,
      "point": "{0.58536585365853877, 0.1166666666666667}"
    },
    {
      "_class": "curvePoint",
      "cornerRadius": 0,
      "curveFrom": "{0.58536585365853877, 1}",
      "curveMode": 1,
      "curveTo": "{0.58536585365853877, 1}",
      "hasCurveFrom": false,
      "hasCurveTo": false,
      "point": "{0.58536585365853877, 1}"
    }
  ],
  "resizingConstraint": 63,
  "resizingType": 0,
  "rotation": 0,
  "shouldBreakMaskChain": false
}