{
  "_class": "shapePath",
  "booleanOperation": -1,
  "do_objectID": "86F86E74-353A-4320-A247-F02D78FD8BE8",
  "edited": true,
  "exportOptions": {
    "_class": "exportOptions",
    "exportFormats": [
    ],
    "includedLayerIds": [
    ],
    "layerOptions": 0,
    "shouldTrim": false
  },
  "frame": {
    "_class": "rect",
    "constrainProportions": false,
    "height": 4.000000000000001,
    "width": 4.000000000000004,
    "x": 0,
    "y": 0
  },
  "isClosed": true,
  "isFixedToViewport": false,
  "isFlippedHorizontal": false,
  "isFlippedVertical": false,
  "isLocked": false,
  "isVisible": true,
  "layerListExpandedType": 0,
  "name": "Path",
  "nameIsFixed": false,
  "pointRadiusBehaviour": 1,
  "points": [
    {
      "_class": "curvePoint",
      "cornerRadius": 0,
      "curveFrom": "{0.22430390598489044, 5.0761210605997395e-16}",
      "curveMode": 4,
      "curveTo": "{0.49999106999339182, 5.0761210605997395e-16}",
      "hasCurveFrom": true,
      "hasCurveTo": false,
      "point": "{0.49999106999339182, 5.0761210605997395e-16}"
    },
    {
      "_class": "curvePoint",
      "cornerRadius": 0,
      "curveFrom": "{0, 0.77569609401511019}",
      "curveMode": 2,
      "curveTo": "{0, 0.22428604597167434}",
      "hasCurveFrom": true,
      "hasCurveTo": true,
      "point": "{0, 0.49999106999339227}"
    },
    {
      "_class": "curvePoint",
      "cornerRadius": 0,
      "curveFrom": "{0.77569609401510964, 1}",
      "curveMode": 2,
      "curveTo": "{0.22428604597167401, 1}",
      "hasCurveFrom": true,
      "hasCurveTo": true,
      "point": "{0.49999106999339182, 1}"
    },
    {
      "_class": "curvePoint",
      "cornerRadius": 0,
      "curveFrom": "{1, 0.22428604597167384}",
      "curveMode": 2,
      "curveTo": "{1, 0.77569609401510964}",
      "hasCurveFrom": true,
      "hasCurveTo": true,
      "point": "{1, 0.49999106999339177}"
    },
    {
      "_class": "curvePoint",
      "cornerRadius": 0,
      "curveFrom": "{0.49999106999339182, 0}",
      "curveMode": 4,
      "curveTo": "{0.77569609401510964, 0}",
      "hasCurveFrom": false,
      "hasCurveTo": true,
      "point": "{0.49999106999339182, 0}"
    }
  ],
  "resizingConstraint": 63,
  "resizingType": 0,
  "rotation": 0,
  "shouldBreakMaskChain": false
}