{
  "_class": "shapeGroup",
  "booleanOperation": -1,
  "clippingMaskMode": 0,
  "do_objectID": "6F981DC2-7804-403D-B87D-F58F1796352C",
  "exportOptions": {
    "_class": "exportOptions",
    "do_objectID": "08E9AD5C-F089-4ABD-A7D2-FD13BF09337F",
    "exportFormats": [
    ],
    "includedLayerIds": [
    ],
    "layerOptions": 0,
    "shouldTrim": false
  },
  "frame": {
    "_class": "rect",
    "constrainProportions": false,
    "do_objectID": "723C4E5A-324F-4AD6-8878-D9AF93B53AD1",
    "height": 20.34069230769234,
    "width": 21.21600000000003,
    "x": 18.85359999999999,
    "y": 0.599923076923081
  },
  "hasClickThrough": false,
  "hasClippingMask": false,
  "isFixedToViewport": false,
  "isFlippedHorizontal": false,
  "isFlippedVertical": false,
  "isLocked": false,
  "isVisible": true,
  "layerListExpandedType": 1,
  "layers": [
    {
      "class": "shapePath",
      "id": "22410E30-4AD3-4781-9319-B8D58470430C"
    },
    {
      "class": "shapePath",
      "id": "DB28A207-5FFD-4718-BAE5-8840EBD366C5"
    }
  ],
  "name": "Path_4",
  "nameIsFixed": false,
  "resizingConstraint": 63,
  "resizingType": 0,
  "rotation": 0,
  "shouldBreakMaskChain": false,
  "style": {
    "_class": "style",
    "do_objectID": "7768D51F-1DAD-496E-AD9C-476EE28008C9",
    "endMarkerType": 0,
    "fills": [
      {
        "_class": "fill",
        "color": {
          "_class": "color",
          "alpha": 1,
          "blue": 0.3647058823529412,
          "green": 0.09803921568627451,
          "red": 0.8745098039215686
        },
        "fillType": 0,
        "isEnabled": true,
        "noiseIndex": 0,
        "noiseIntensity": 0,
        "patternFillType": 1,
        "patternTileScale": 1
      }
    ],
    "miterLimit": 10,
    "startMarkerType": 0,
    "windingRule": 0
  },
  "windingRule": 0
}